__init__.py
mermaid2image.py
mermaid2img-0.0.1.dist-info/LICENSE
mermaid2img-0.0.1.dist-info/METADATA
mermaid2img-0.0.1.dist-info/WHEEL
mermaid2img-0.0.1.dist-info/entry_points.txt
mermaid2img-0.0.1.dist-info/top_level.txt
mermaid2img-0.0.1.dist-info/RECORD
