Metadata-Version: 2.1
Name: mermaid2img
Version: 0.0.1
Summary: Mermaid markdown to image using https://mermaid.ink/img/ API.
Author-email: Matevž <matevzlesko@gmail.com>
License: GNU GENERAL PUBLIC LICENSE
Classifier: Development Status :: 2 - Pre-Alpha
Classifier: Programming Language :: Python :: 3
Classifier: Operating System :: OS Independent
Requires-Python: >=3.8
License-File: LICENSE
Requires-Dist: requests >=2.32.3
Requires-Dist: matplotlib >=3.9.2
Requires-Dist: pillow >=10.4.0
